image_processing_package/__init__.py
image_processing_package/processing/__init__.py
image_processing_package/processing/combination.py
image_processing_package/processing/transformation.py
image_processing_package/utils/__init__.py
image_processing_package/utils/io.py
image_processing_package/utils/plot.py
image_processing_package-0.1.1.dist-info/METADATA
image_processing_package-0.1.1.dist-info/WHEEL
image_processing_package-0.1.1.dist-info/top_level.txt
image_processing_package-0.1.1.dist-info/RECORD
