Metadata-Version: 2.1
Name: image-processing-package
Version: 0.1.1
Summary: Criação de pacotes de processamento de imagens em Python
Home-page: https://github.com/Jucicarla/criacao_de_pacotes_processamento_imagens_Python
Author: Jucicarla Pires
Author-email: jucipires@gmail.com
License: UNKNOWN
Platform: UNKNOWN
Requires-Python: >=3.8
Requires-Dist: matplotlib
Requires-Dist: numpy
Requires-Dist: scikit-image (>=0.16.1)
